benchlingapi/__init__.py
benchlingapi/__version__.py
benchlingapi/exceptions.py
benchlingapi/models/__init__.py
benchlingapi/models/base.py
benchlingapi/models/mixins.py
benchlingapi/models/models.py
benchlingapi/models/schema.py
benchlingapi/session.py
benchlingapi/utils.py
benchlingapi-2.1.12.dist-info/LICENSE
benchlingapi-2.1.12.dist-info/WHEEL
benchlingapi-2.1.12.dist-info/METADATA
benchlingapi-2.1.12.dist-info/RECORD
