Metadata-Version: 2.1
Name: benchlingapi
Version: 2.1.12
Summary: An unofficial python wrapper for the Benchling API
Home-page: https://www.github.com/klavinslab/benchling-api
Author: Justin Vrana
Author-email: justin.vrana@gmail.com
Requires-Python: >=3.5.2,<4.0.0
Classifier: Development Status :: 4 - Beta
Classifier: Intended Audience :: Science/Research
Classifier: Programming Language :: Python :: 3
Classifier: Programming Language :: Python :: 3.6
Classifier: Programming Language :: Python :: 3.7
Classifier: Topic :: Scientific/Engineering :: Bio-Informatics
Requires-Dist: bs4 (>=0.0.1,<0.0.2)
Requires-Dist: inflection (>=0.3.1,<0.4.0)
Requires-Dist: marshmallow (>=3.2,<4.0)
Requires-Dist: requests (>=2.22,<3.0)
Requires-Dist: urlopen (>=1.0,<2.0)
Project-URL: Documentation, http://klavinslab.org/benchling-api/
Project-URL: Repository, https://pypi.org/project/benchlingapi/
